maleo/mcu/__init__.py
maleo/mcu/constants/__init__.py
maleo/mcu/constants/analysis.py
maleo/mcu/constants/ascvd_risk.py
maleo/mcu/constants/checkup.py
maleo/mcu/constants/client.py
maleo/mcu/constants/examination.py
maleo/mcu/constants/finding.py
maleo/mcu/constants/finding_parameter.py
maleo/mcu/constants/parameter.py
maleo/mcu/constants/patient.py
maleo/mcu/constants/rule.py
maleo/mcu/enums/__init__.py
maleo/mcu/enums/analysis.py
maleo/mcu/enums/ascvd_risk.py
maleo/mcu/enums/checkup.py
maleo/mcu/enums/client.py
maleo/mcu/enums/examination.py
maleo/mcu/enums/finding.py
maleo/mcu/enums/finding_parameter.py
maleo/mcu/enums/parameter.py
maleo/mcu/enums/patient.py
maleo/mcu/enums/rule.py
maleo/mcu/mixins/__init__.py
maleo/mcu/mixins/analysis.py
maleo/mcu/mixins/ascvd_risk.py
maleo/mcu/mixins/checkup.py
maleo/mcu/mixins/client.py
maleo/mcu/mixins/common.py
maleo/mcu/mixins/examination.py
maleo/mcu/mixins/finding.py
maleo/mcu/mixins/finding_parameter.py
maleo/mcu/mixins/parameter.py
maleo/mcu/mixins/patient.py
maleo/mcu/mixins/rule.py
maleo/mcu/schemas/__init__.py
maleo/mcu/schemas/analysis.py
maleo/mcu/schemas/ascvd_risk.py
maleo/mcu/schemas/checkup.py
maleo/mcu/schemas/client.py
maleo/mcu/schemas/common.py
maleo/mcu/schemas/document.py
maleo/mcu/schemas/examination.py
maleo/mcu/schemas/finding.py
maleo/mcu/schemas/parameter.py
maleo/mcu/schemas/patient.py
maleo/mcu/schemas/rule.py
maleo/mcu/types/__init__.py
maleo/mcu/types/analysis.py
maleo/mcu/types/ascvd_risk.py
maleo/mcu/types/checkup.py
maleo/mcu/types/client.py
maleo/mcu/types/examination.py
maleo/mcu/types/finding.py
maleo/mcu/types/finding_parameter.py
maleo/mcu/types/parameter.py
maleo/mcu/types/patient.py
maleo/mcu/types/rule.py
maleo/mcu/utils/__init__.py
maleo/mcu/utils/examination.py
maleo/mcu/utils/finding.py
maleo/mcu/utils/parameter.py
maleo/mcu/utils/rule.py
maleo_mcu-0.1.5.dist-info/licenses/LICENSE
maleo_mcu-0.1.5.dist-info/METADATA
maleo_mcu-0.1.5.dist-info/WHEEL
maleo_mcu-0.1.5.dist-info/top_level.txt
maleo_mcu-0.1.5.dist-info/RECORD
